LICENSE
MANIFEST.in
README
chiki_patch.py
setup.py
chiki_patch.egg-info/PKG-INFO
chiki_patch.egg-info/SOURCES.txt
chiki_patch.egg-info/dependency_links.txt
chiki_patch.egg-info/not-zip-safe
chiki_patch.egg-info/requires.txt
chiki_patch.egg-info/top_level.txt