Metadata-Version: 1.0
Name: chiki-patch
Version: 0.0.1
Summary: chiki patch libs.
Home-page: https://github.com/endsh/chiki-patch
Author: Linshao
Author-email: 438985635@qq.com
License: UNKNOWN
Platform: any
